source_woocommerce/__init__.py
source_woocommerce/manifest.yaml
source_woocommerce/run.py
source_woocommerce/source.py
airbyte_source_woocommerce-0.4.12.dist-info/METADATA
airbyte_source_woocommerce-0.4.12.dist-info/WHEEL
airbyte_source_woocommerce-0.4.12.dist-info/entry_points.txt
airbyte_source_woocommerce-0.4.12.dist-info/RECORD
