Metadata-Version: 2.1
Name: airbyte-source-woocommerce
Version: 0.4.12
Summary: Source implementation for Woocommerce.
Home-page: https://airbyte.com
License: MIT
Author: Airbyte
Author-email: contact@airbyte.io
Requires-Python: >=3.10,<3.12
Classifier: License :: OSI Approved :: MIT License
Classifier: Programming Language :: Python :: 3
Classifier: Programming Language :: Python :: 3.10
Classifier: Programming Language :: Python :: 3.11
Requires-Dist: airbyte-cdk (>=4,<5)
Project-URL: Documentation, https://docs.airbyte.com/integrations/sources/woocommerce
Project-URL: Repository, https://github.com/airbytehq/airbyte
